AnjingMingxiangdeLiliangX10/Dockerfile
AnjingMingxiangdeLiliangX10/README.md
AnjingMingxiangdeLiliangX10/__init__.py
AnjingMingxiangdeLiliangX10/__main__.py
AnjingMingxiangdeLiliangX10/file.epub
AnjingMingxiangdeLiliangX10/index.html
AnjingMingxiangdeLiliangX10/css/__init__.py
AnjingMingxiangdeLiliangX10/css/annotations.css
AnjingMingxiangdeLiliangX10/css/main.css
AnjingMingxiangdeLiliangX10/css/normalize.css
AnjingMingxiangdeLiliangX10/css/popup.css
AnjingMingxiangdeLiliangX10/font/__init__.py
AnjingMingxiangdeLiliangX10/font/fontello.eot
AnjingMingxiangdeLiliangX10/font/fontello.svg
AnjingMingxiangdeLiliangX10/font/fontello.ttf
AnjingMingxiangdeLiliangX10/font/fontello.woff
AnjingMingxiangdeLiliangX10/img/__init__.py
AnjingMingxiangdeLiliangX10/img/annotator-glyph-sprite.png
AnjingMingxiangdeLiliangX10/img/annotator-icon-sprite.png
AnjingMingxiangdeLiliangX10/img/apple-touch-icon.png
AnjingMingxiangdeLiliangX10/img/cancelfullscreen.png
AnjingMingxiangdeLiliangX10/img/close.png
AnjingMingxiangdeLiliangX10/img/fullscreen.png
AnjingMingxiangdeLiliangX10/img/loader.gif
AnjingMingxiangdeLiliangX10/img/menu-icon.png
AnjingMingxiangdeLiliangX10/img/save.png
AnjingMingxiangdeLiliangX10/img/saved.png
AnjingMingxiangdeLiliangX10/img/settings-s.png
AnjingMingxiangdeLiliangX10/img/settings.png
AnjingMingxiangdeLiliangX10/img/star.png
AnjingMingxiangdeLiliangX10/js/__init__.py
AnjingMingxiangdeLiliangX10/js/epub.js
AnjingMingxiangdeLiliangX10/js/epub.min.js
AnjingMingxiangdeLiliangX10/js/epub.min.map
AnjingMingxiangdeLiliangX10/js/hooks.min.js
AnjingMingxiangdeLiliangX10/js/hooks.min.map
AnjingMingxiangdeLiliangX10/js/reader.js
AnjingMingxiangdeLiliangX10/js/reader.js.map
AnjingMingxiangdeLiliangX10/js/reader.min.js
AnjingMingxiangdeLiliangX10/js/reader.min.map
AnjingMingxiangdeLiliangX10/js/hooks/__init__.py
AnjingMingxiangdeLiliangX10/js/hooks/extensions/__init__.py
AnjingMingxiangdeLiliangX10/js/hooks/extensions/highlight.js
AnjingMingxiangdeLiliangX10/js/libs/__init__.py
anjing_mingxiangde_liliang_x10-2022.10.9.1.dist-info/METADATA
anjing_mingxiangde_liliang_x10-2022.10.9.1.dist-info/WHEEL
anjing_mingxiangde_liliang_x10-2022.10.9.1.dist-info/entry_points.txt
anjing_mingxiangde_liliang_x10-2022.10.9.1.dist-info/top_level.txt
anjing_mingxiangde_liliang_x10-2022.10.9.1.dist-info/RECORD
